NeuralNetworks/__init__.py
NeuralNetworks/Dependances/__init__.py
NeuralNetworks/Dependances/matplot.py
NeuralNetworks/Dependances/pytorch.py
NeuralNetworks/MLP/FourierFeatures.py
NeuralNetworks/MLP/Layers.py
NeuralNetworks/MLP/__init__.py
NeuralNetworks/MLP/inference.py
NeuralNetworks/Trainer/__init__.py
NeuralNetworks/Trainer/dynamic_learning_rate.py
NeuralNetworks/Trainer/sample_data.py
NeuralNetworks/Trainer/train.py
NeuralNetworks/UI/Learnings.py
NeuralNetworks/UI/Losses.py
NeuralNetworks/UI/__init__.py
NeuralNetworks/shared/__init__.py
NeuralNetworks/shared/module.py
neuralnetworks-0.2.6.dist-info/licenses/LICENSE
neuralnetworks-0.2.6.dist-info/METADATA
neuralnetworks-0.2.6.dist-info/WHEEL
neuralnetworks-0.2.6.dist-info/top_level.txt
neuralnetworks-0.2.6.dist-info/RECORD
