Metadata-Version: 2.4
Name: NeuralNetworks
Version: 0.2.6
Summary: Multi-Layer Perceptrons with multi-Fourier encoding, variable learning rate, visualization and PyTorch compilation
Author-email: Alexandre Brun <alexandre51160@gmail.com>
License: GPL-3.0-or-later
Project-URL: Documentation, https://xxxfetraxxx.github.io/NeuralNetworks/
Project-URL: Source, https://github.com/xXxFetraxXx/NeuralNetworks
Classifier: Programming Language :: Python :: 3
Classifier: License :: OSI Approved :: GNU General Public License v3 or later (GPLv3+)
Classifier: Operating System :: OS Independent
Requires-Python: >=3.9
License-File: LICENSE
Requires-Dist: numpy>=1.25
Requires-Dist: matplotlib>=3.10
Requires-Dist: tqdm>=4.66
Requires-Dist: torch<3.0,>=2.9.1
Requires-Dist: torchvision<1.0,>=0.24
Requires-Dist: torchaudio<3.0,>=2.9
Requires-Dist: torchmetrics>=1.8
Requires-Dist: visualtorch>=0.2
Requires-Dist: random-fourier-features-pytorch>=1.0
Requires-Dist: IPython>=8.16
Requires-Dist: requests
Requires-Dist: airfrans
Requires-Dist: scipy
Requires-Dist: pandas
Dynamic: license-file
